MANIFEST.in
README.md
VERSION
setup.py
cowboybike/__init__.py
cowboybike/cowboybike.py
cowboybike.egg-info/PKG-INFO
cowboybike.egg-info/SOURCES.txt
cowboybike.egg-info/dependency_links.txt
cowboybike.egg-info/top_level.txt